pyfacl/__init__.py
pyfacl/cli.py
pyfacl/logger.py
pyfacl/pyfacl.py
pyfacl/pyfacl_trace.py
pyfacl-1.2.0.dist-info/LICENSE
pyfacl-1.2.0.dist-info/METADATA
pyfacl-1.2.0.dist-info/WHEEL
pyfacl-1.2.0.dist-info/entry_points.txt
pyfacl-1.2.0.dist-info/RECORD
