Metadata-Version: 2.3
Name: pyfacl
Version: 1.2.0
Summary: Package to manage access control using POSIX ACLs
License: MIT
Author: tobiaspk
Author-email: tobiaspk1@gmail.com
Requires-Python: >=3.12
Classifier: License :: OSI Approved :: MIT License
Classifier: Programming Language :: Python :: 3
Classifier: Programming Language :: Python :: 3.12
Classifier: Programming Language :: Python :: 3.13
Provides-Extra: dev
Requires-Dist: black (>=23.0.0) ; extra == "dev"
Requires-Dist: flake8 (>=6.0.0) ; extra == "dev"
Requires-Dist: isort (>=5.12.0) ; extra == "dev"
Requires-Dist: pre-commit (>=3.0.0) ; extra == "dev"
Requires-Dist: pytest (>=7.0.0) ; extra == "dev"
Requires-Dist: typer (>=0.15.0)
